fbgemm_gpu/__init__.py
fbgemm_gpu/asmjit.so
fbgemm_gpu/batched_unary_embeddings_ops.py
fbgemm_gpu/enums.py
fbgemm_gpu/fbgemm.so
fbgemm_gpu/fbgemm_gpu_config.so
fbgemm_gpu/fbgemm_gpu_embedding_inplace_ops.so
fbgemm_gpu/fbgemm_gpu_py.so
fbgemm_gpu/fbgemm_gpu_sparse_async_cumsum.so
fbgemm_gpu/fbgemm_gpu_tbe_cache.so
fbgemm_gpu/fbgemm_gpu_tbe_common.so
fbgemm_gpu/fbgemm_gpu_tbe_index_select.so
fbgemm_gpu/fbgemm_gpu_tbe_inference.so
fbgemm_gpu/fbgemm_gpu_tbe_optimizers.so
fbgemm_gpu/fbgemm_gpu_tbe_training_backward.so
fbgemm_gpu/fbgemm_gpu_tbe_training_backward_dense.so
fbgemm_gpu/fbgemm_gpu_tbe_training_backward_gwd.so
fbgemm_gpu/fbgemm_gpu_tbe_training_backward_pt2.so
fbgemm_gpu/fbgemm_gpu_tbe_training_backward_split_host.so
fbgemm_gpu/fbgemm_gpu_tbe_training_backward_vbe.so
fbgemm_gpu/fbgemm_gpu_tbe_training_forward.so
fbgemm_gpu/fbgemm_gpu_tbe_utils.so
fbgemm_gpu/metrics.py
fbgemm_gpu/permute_pooled_embedding_modules.py
fbgemm_gpu/permute_pooled_embedding_modules_split.py
fbgemm_gpu/quantize_comm.py
fbgemm_gpu/quantize_utils.py
fbgemm_gpu/runtime_monitor.py
fbgemm_gpu/sparse_ops.py
fbgemm_gpu/split_embedding_configs.py
fbgemm_gpu/split_embedding_inference_converter.py
fbgemm_gpu/split_embedding_optimizer_ops.py
fbgemm_gpu/split_embedding_utils.py
fbgemm_gpu/split_table_batched_embeddings_ops.py
fbgemm_gpu/split_table_batched_embeddings_ops_common.py
fbgemm_gpu/split_table_batched_embeddings_ops_inference.py
fbgemm_gpu/split_table_batched_embeddings_ops_training.py
fbgemm_gpu/split_table_batched_embeddings_ops_training_common.py
fbgemm_gpu/ssd_split_table_batched_embeddings_ops.py
fbgemm_gpu/tbe_input_multiplexer.py
fbgemm_gpu/uvm.py
fbgemm_gpu/config/__init__.py
fbgemm_gpu/config/feature_list.py
fbgemm_gpu/docs/__init__.py
fbgemm_gpu/docs/common.py
fbgemm_gpu/docs/examples.py
fbgemm_gpu/docs/jagged_tensor_ops.py
fbgemm_gpu/docs/merge_pooled_embedding_ops.py
fbgemm_gpu/docs/permute_pooled_embedding_ops.py
fbgemm_gpu/docs/quantize_ops.py
fbgemm_gpu/docs/sparse_ops.py
fbgemm_gpu_nightly-2025.12.29.dist-info/METADATA
fbgemm_gpu_nightly-2025.12.29.dist-info/WHEEL
fbgemm_gpu_nightly-2025.12.29.dist-info/top_level.txt
fbgemm_gpu_nightly-2025.12.29.dist-info/RECORD
